<Properties StartupConfiguration="{A5D15A1B-55E8-0474-87A7-191828B83106}|">
  <MonoDevelop.Ide.Workbench ActiveDocument="Assets/Scripts/HexMapPosition.cs">
    <Files>
      <File FileName="Assets/Scripts/HexMapGenerator.cs" Line="353" Column="13" />
      <File FileName="Assets/Scripts/Animation/AnimationManager.cs" Line="35" Column="41" />
      <File FileName="Assets/Scripts/Animation/AnimatableMapHex.cs" Line="80" Column="1" />
      <File FileName="Assets/Scripts/UnityMapHex.cs" />
      <File FileName="Assets/Scripts/HexMapPosition.cs" Line="2" Column="31" />
    </Files>
    <Pads>
      <Pad Id="ProjectPad">
        <State name="__root__">
          <Node name="hexmap-practice" expanded="True">
            <Node name="Assets" expanded="True">
              <Node name="Scripts" expanded="True">
                <Node name="Animation" expanded="True">
                  <Node name="TimeTransform" expanded="True" />
                </Node>
                <Node name="HexMapPosition.cs" selected="True" />
              </Node>
            </Node>
          </Node>
        </State>
      </Pad>
      <Pad Id="MonoDevelop.Debugger.WatchPad">
        <State>
          <Value>referenceHexPosition.positio</Value>
          <Value>placement</Value>
          <Value>position</Value>
          <Value>nextReferenceHex.getPosition()</Value>
          <Value>newPosition</Value>
          <Value>placementGrid[newPosition.x,newPosition.y]</Value>
          <Value>Enum.GetValues(typeof(HexEdgeEnum)).Cast&lt;HexEdgeEnum&gt;().ToList()</Value>
        </State>
      </Pad>
    </Pads>
  </MonoDevelop.Ide.Workbench>
  <MonoDevelop.Ide.DebuggingService.PinnedWatches />
  <MonoDevelop.Ide.Workspace ActiveConfiguration="Debug" />
  <MonoDevelop.Ide.ItemProperties.Assembly-CSharp PreferredExecutionTarget="9f5749b5-2f2c-4ae8-9796-bbc0b6dbcf54" />
  <MonoDevelop.Ide.DebuggingService.Breakpoints>
    <BreakpointStore>
      <Breakpoint enabled="false" file="/Users/jwoolley/Personal/git/hexmap-practice/Assets/Scripts/HexMapGenerator.cs" relfile="Assets/Scripts/HexMapGenerator.cs" line="143" column="1" />
      <Breakpoint file="/Users/jwoolley/Personal/git/hexmap-practice/Assets/Scripts/HexMapGenerator.cs" relfile="Assets/Scripts/HexMapGenerator.cs" line="200" column="1" />
    </BreakpointStore>
  </MonoDevelop.Ide.DebuggingService.Breakpoints>
  <MultiItemStartupConfigurations />
</Properties>